r2r_protocol/__init__.py
r2r_protocol/client.py
r2r_protocol/message_format.py
r2r_protocol/message_types.py
r2r_protocol/payloads.py
r2r_protocol-2.0.0.dist-info/LICENSE
r2r_protocol-2.0.0.dist-info/METADATA
r2r_protocol-2.0.0.dist-info/WHEEL
r2r_protocol-2.0.0.dist-info/RECORD
