Metadata-Version: 2.3
Name: r2r_protocol
Version: 2.0.0
Summary: Robot-to-Robot (R2R) Communication Protocol SDK in Python
License: Apache-2.0
Author: Tech-Parivartan
Author-email: techparivartan022@gmail.com
Requires-Python: >=3.7
Classifier: License :: OSI Approved :: Apache Software License
Classifier: Programming Language :: Python :: 3
Classifier: Programming Language :: Python :: 3.7
Classifier: Programming Language :: Python :: 3.8
Classifier: Programming Language :: Python :: 3.9
Classifier: Programming Language :: Python :: 3.10
Classifier: Programming Language :: Python :: 3.11
Classifier: Programming Language :: Python :: 3.12
Classifier: Programming Language :: Python :: 3.13
